t2m/__init__.py
t2m/retweet.tmpl
t2m-0.1.0.data/data/LICENSE
t2m-0.1.0.data/data/README.md
t2m-0.1.0.dist-info/DESCRIPTION.rst
t2m-0.1.0.dist-info/METADATA
t2m-0.1.0.dist-info/RECORD
t2m-0.1.0.dist-info/WHEEL
t2m-0.1.0.dist-info/entry_points.txt
t2m-0.1.0.dist-info/metadata.json
t2m-0.1.0.dist-info/top_level.txt
