Metadata-Version: 2.0
Name: t2m
Version: 0.1.0
Summary: Twitter to Mastodon timeline forwarding tool
Home-page: https://github.com/Psycojoker/t2m
Author: Laurent Peuch and al.
Author-email: cortex@worlddomination.be
License: GPLv3
Keywords: mastodon twitter bot robot
Platform: UNKNOWN
Classifier: Development Status :: 3 - Alpha
Classifier: Intended Audience :: Other Audience
Classifier: Environment :: Console
Classifier: Topic :: Communications
Classifier: Topic :: Utilities
Classifier: License :: OSI Approved :: GNU General Public License v3 (GPLv3)
Classifier: Programming Language :: Python :: 2
Classifier: Programming Language :: Python :: 2.7
Classifier: Programming Language :: Python :: 3
Classifier: Programming Language :: Python :: 3.5
Requires-Dist: Mastodon.py
Requires-Dist: python-twitter
Requires-Dist: requests
Requires-Dist: pyyaml
Requires-Dist: argh
